rescupy/__init__.py
rescupy/aobasis.py
rescupy/atoms.py
rescupy/bandstructure.py
rescupy/bandunfolding.py
rescupy/base.py
rescupy/basis.py
rescupy/cell.py
rescupy/checkconv.py
rescupy/cmd.py
rescupy/current.py
rescupy/data/__init__.py
rescupy/data/kpoint.py
rescupy/data/units.py
rescupy/data/xc.py
rescupy/defect.py
rescupy/densityofstates.py
rescupy/dielectric.py
rescupy/dipole.py
rescupy/dos.py
rescupy/eig.py
rescupy/energy.py
rescupy/eos.py
rescupy/ewald.py
rescupy/extpot.py
rescupy/fdforces.py
rescupy/geometry.py
rescupy/hamiltonian.py
rescupy/io/__init__.py
rescupy/io/calculators.py
rescupy/io/xyz.py
rescupy/iv.py
rescupy/jsonio.py
rescupy/kpoint.py
rescupy/localdos.py
rescupy/matlab/readfrc.m
rescupy/mix.py
rescupy/mpidist.py
rescupy/mulliken.py
rescupy/orb.py
rescupy/pop.py
rescupy/pspot.py
rescupy/relax.py
rescupy/restart.py
rescupy/scattering.py
rescupy/solver.py
rescupy/species.py
rescupy/system.py
rescupy/totalenergy.py
rescupy/transmission.py
rescupy/twoprobe.py
rescupy/utils.py
rescupy/vbm.py
rescupy/wavefunction.py
rescupy/xc.py
rescupy-1.1.0rc2.dist-info/LICENSE.txt
rescupy-1.1.0rc2.dist-info/WHEEL
rescupy-1.1.0rc2.dist-info/METADATA
rescupy-1.1.0rc2.dist-info/RECORD
